setup.py
sectioner/__init__.py
sectioner/asset.py
sectioner/image.py
sectioner/info.py
sectioner/parser.py
sectioner/project.py
sectioner/sectioner.py
sectioner/template.py
sectioner/watcher.py
sectioner/writer.py
sectioner.egg-info/PKG-INFO
sectioner.egg-info/SOURCES.txt
sectioner.egg-info/dependency_links.txt
sectioner.egg-info/entry_points.txt
sectioner.egg-info/requires.txt
sectioner.egg-info/top_level.txt
sectioner/data/data.xml
sectioner/data/example.xml
sectioner/data/image_0.jpg
sectioner/data/image_1.jpg
sectioner/data/index.html
sectioner/data/lodash.js
sectioner/data/master.html
sectioner/data/media.html
sectioner/data/page.html
sectioner/data/sectioner.js
sectioner/data/styles.css
sectioner/data/velocity.js
sectioner/data/zepto.js