Metadata-Version: 1.1
Name: sectioner
Version: 0.1.3
Summary: A site section static builder
Home-page: https://github.com/atelier-cartographique/static-sectioner
Author: Pierre Marchand
Author-email: pierremarc07@gmail.com
License: Affero GPL3
Platform: UNKNOWN
Classifier: Development Status :: 3 - Alpha
Classifier: Intended Audience :: Developers
Classifier: Topic :: Software Development :: Build Tools
Classifier: License :: OSI Approved :: GNU Affero General Public License v3 or later (AGPLv3+)
Classifier: Operating System :: POSIX
Classifier: Programming Language :: Python
Classifier: Programming Language :: Python :: 3.4
